finitelycomputable/idtrust_common/__init__.py
finitelycomputable/idtrust_common/helpers_for_tests.py
finitelycomputable/idtrust_common/logic.py
finitelycomputable/idtrust_common/strategies.py
finitelycomputable/idtrust_common/templates/exchange_form.html
finitelycomputable/idtrust_common/templates/interaction.html
finitelycomputable/idtrust_common/templates/interaction_begin.html
finitelycomputable_idtrust_common-25.7.dist-info/METADATA
finitelycomputable_idtrust_common-25.7.dist-info/WHEEL
finitelycomputable_idtrust_common-25.7.dist-info/top_level.txt
finitelycomputable_idtrust_common-25.7.dist-info/RECORD
